alu.v
module alu (
    input  wire [7:0] A,
    input  wire [7:0] B,
    input  wire [2:0] ALU_Control,
    output reg  [7:0] ALU_Result,
    output wire        Zero
);

    // Combinational ALU
    always @* begin
        case (ALU_Control)
            3'b000: ALU_Result = A + B;   // ADD
            3'b001: ALU_Result = A - B;   // SUB
            3'b010: ALU_Result = A & B;   // AND
            3'b011: ALU_Result = A | B;   // OR
            default: ALU_Result = 8'h00;  // Safe default
        endcase
    end

    assign Zero = (ALU_Result == 8'h00);

endmodule

tb_alu.v
`timescale 1ns/1ps

module tb_alu;
    reg  [7:0] A;
    reg  [7:0] B;
    reg  [2:0] ALU_Control;
    wire [7:0] ALU_Result;
    wire        Zero;

    reg  [7:0] vals [0:7];
    integer i, j;

    alu dut (
        .A(A),
        .B(B),
        .ALU_Control(ALU_Control),
        .ALU_Result(ALU_Result),
        .Zero(Zero)
    );

    integer errors;
    integer tests;

    // Checks one ALU operation for a single (A, B) pair.
    task check;
        input [2:0] control;
        input [7:0] a_in;
        input [7:0] b_in;
        reg   [7:0] exp;
        reg          exp_zero;
        begin
            ALU_Control = control;
            A = a_in;
            B = b_in;
            #1; // allow combinational outputs to settle

            case (control)
                3'b000: exp = (a_in + b_in) & 8'hFF; // ADD
                3'b001: exp = (a_in - b_in) & 8'hFF; // SUB
                3'b010: exp = a_in & b_in;           // AND
                3'b011: exp = a_in | b_in;           // OR
                default: exp = 8'h00;
            endcase

            exp_zero = (exp == 8'h00);
            tests = tests + 1;

            if (ALU_Result !== exp) begin
                errors = errors + 1;
                $display("FAIL: control=%b A=%h B=%h => ALU_Result=%h (expected %h)",
                    control, a_in, b_in, ALU_Result, exp);
            end

            if (Zero !== exp_zero) begin
                errors = errors + 1;
                $display("FAIL: control=%b A=%h B=%h => Zero=%b (expected %b)",
                    control, a_in, b_in, Zero, exp_zero);
            end
        end
    endtask

    initial begin
        $dumpfile("alu_waves.vcd");
        $dumpvars(0, tb_alu);
        errors = 0;
        tests  = 0;

        // Explicit edge cases that should produce zero.
        check(3'b000, 8'h00, 8'h00); // ADD: 0 + 0 = 0
        check(3'b000, 8'hFF, 8'h01); // ADD: 255 + 1 = 0 (wrap)
        check(3'b000, 8'h80, 8'h80); // ADD: 128 + 128 = 0 (wrap)

        check(3'b001, 8'h00, 8'h00); // SUB: 0 - 0 = 0
        check(3'b001, 8'h12, 8'h12); // SUB: A - A = 0
        check(3'b001, 8'hFF, 8'hFF); // SUB: 255 - 255 = 0

        check(3'b010, 8'h00, 8'hAB); // AND: 0 & x = 0
        check(3'b010, 8'h0F, 8'hF0); // AND: 0000 -> 0
        check(3'b010, 8'hAA, 8'h55); // AND: pattern -> 0

        check(3'b011, 8'h00, 8'h00); // OR: 0 | 0 = 0
        check(3'b011, 8'h0F, 8'hF0); // OR: 0x0F | 0xF0 = 0xFF (non-zero)

        // Explicit underflow/overflow behavior (mod 256).
        check(3'b001, 8'h00, 8'h01); // SUB: 0 - 1 = 0xFF (wrap underflow)
        check(3'b000, 8'hFE, 8'h02); // ADD: 0xFE + 0x02 = 0x00 (wrap)

        // Broad sweep across representative values.
        vals[0] = 8'h00;
        vals[1] = 8'h01;
        vals[2] = 8'h02;
        vals[3] = 8'h03;
        vals[4] = 8'h7F;
        vals[5] = 8'h80;
        vals[6] = 8'hFE;
        vals[7] = 8'hFF;

        for (i = 0; i < 8; i = i + 1) begin
            for (j = 0; j < 8; j = j + 1) begin
                check(3'b000, vals[i], vals[j]); // ADD
                check(3'b001, vals[i], vals[j]); // SUB
                check(3'b010, vals[i], vals[j]); // AND
                check(3'b011, vals[i], vals[j]); // OR
            end
        end

        if (errors == 0) begin
            $display("PASS: %0d tests passed.", tests);
        end else begin
            $display("DONE: %0d tests, %0d errors.", tests, errors);
        end

        $finish;
    end
endmodule

.gitignore/alu_waves.vcd
$date
	Fri Mar 20 14:24:50 2026
$end
$version
	Icarus Verilog
$end
$timescale
	1ps
$end
$scope module tb_alu $end
$var wire 1 ! Zero $end
$var wire 8 " ALU_Result [7:0] $end
$var reg 8 # A [7:0] $end
$var reg 3 $ ALU_Control [2:0] $end
$var reg 8 % B [7:0] $end
$var integer 32 & errors [31:0] $end
$var integer 32 ' i [31:0] $end
$var integer 32 ( j [31:0] $end
$var integer 32 ) tests [31:0] $end
$scope module dut $end
$var wire 8 * A [7:0] $end
$var wire 3 + ALU_Control [2:0] $end
$var wire 8 , B [7:0] $end
$var wire 1 ! Zero $end
$var reg 8 - ALU_Result [7:0] $end
$upscope $end
$scope task check $end
$var reg 8 . a_in [7:0] $end
$var reg 8 / b_in [7:0] $end
$var reg 3 0 control [2:0] $end
$var reg 8 1 exp [7:0] $end
$var reg 1 2 exp_zero $end
$upscope $end
$upscope $end
$enddefinitions $end
$comment Show the parameter values. $end
$dumpall
$end
#0
$dumpvars
x2
bx 1
b0 0
b0 /
b0 .
b0 -
b0 ,
b0 +
b0 *
b0 )
bx (
bx '
b0 &
b0 %
b0 $
b0 #
b0 "
1!
$end
#1000
b1 %
b1 ,
b11111111 #
b11111111 *
b1 /
b11111111 .
b1 )
12
b0 1
#2000
b10000000 %
b10000000 ,
b10000000 #
b10000000 *
b10000000 /
b10000000 .
b10 )
#3000
b0 %
b0 ,
b0 #
b0 *
b1 $
b1 +
b0 /
b0 .
b1 0
b11 )
#4000
b10010 %
b10010 ,
b10010 #
b10010 *
b10010 /
b10010 .
b100 )
#5000
b11111111 %
b11111111 ,
b11111111 #
b11111111 *
b11111111 /
b11111111 .
b101 )
#6000
b10101011 %
b10101011 ,
b0 #
b0 *
b10 $
b10 +
b10101011 /
b0 .
b10 0
b110 )
#7000
b11110000 %
b11110000 ,
b1111 #
b1111 *
b11110000 /
b1111 .
b111 )
#8000
b1010101 %
b1010101 ,
b10101010 #
b10101010 *
b1010101 /
b10101010 .
b1000 )
#9000
b0 %
b0 ,
b0 #
b0 *
b11 $
b11 +
b0 /
b0 .
b11 0
b1001 )
#10000
0!
b11111111 "
b11111111 -
b11110000 %
b11110000 ,
b1111 #
b1111 *
b11110000 /
b1111 .
b1010 )
#11000
b1 %
b1 ,
b0 #
b0 *
b1 $
b1 +
b1 /
b0 .
b1 0
b1011 )
02
b11111111 1
#12000
1!
b0 "
b0 -
b10 %
b10 ,
b11111110 #
b11111110 *
b0 $
b0 +
b10 /
b11111110 .
b0 0
b1100 )
#13000
b0 %
b0 ,
b0 #
b0 *
b0 /
b0 .
b0 (
b0 '
b1101 )
12
b0 1
#14000
b1 $
b1 +
b1 0
b1110 )
#15000
b10 $
b10 +
b10 0
b1111 )
#16000
b11 $
b11 +
b11 0
b10000 )
#17000
0!
b1 "
b1 -
b1 %
b1 ,
b0 $
b0 +
b1 /
b0 0
b1 (
b10001 )
#18000
b11111111 "
b11111111 -
b1 $
b1 +
b1 0
b10010 )
02
b1 1
#19000
1!
b0 "
b0 -
b10 $
b10 +
b10 0
b10011 )
b11111111 1
#20000
0!
b1 "
b1 -
b11 $
b11 +
b11 0
b10100 )
12
b0 1
#21000
b10 "
b10 -
b10 %
b10 ,
b0 $
b0 +
b10 /
b0 0
b10 (
b10101 )
02
b1 1
#22000
b11111110 "
b11111110 -
b1 $
b1 +
b1 0
b10110 )
b10 1
#23000
1!
b0 "
b0 -
b10 $
b10 +
b10 0
b10111 )
b11111110 1
#24000
0!
b10 "
b10 -
b11 $
b11 +
b11 0
b11000 )
12
b0 1
#25000
b11 "
b11 -
b11 %
b11 ,
b0 $
b0 +
b11 /
b0 0
b11 (
b11001 )
02
b10 1
#26000
b11111101 "
b11111101 -
b1 $
b1 +
b1 0
b11010 )
b11 1
#27000
1!
b0 "
b0 -
b10 $
b10 +
b10 0
b11011 )
b11111101 1
#28000
0!
b11 "
b11 -
b11 $
b11 +
b11 0
b11100 )
12
b0 1
#29000
b1111111 "
b1111111 -
b1111111 %
b1111111 ,
b0 $
b0 +
b1111111 /
b0 0
b100 (
b11101 )
02
b11 1
#30000
b10000001 "
b10000001 -
b1 $
b1 +
b1 0
b11110 )
b1111111 1
#31000
1!
b0 "
b0 -
b10 $
b10 +
b10 0
b11111 )
b10000001 1
#32000
0!
b1111111 "
b1111111 -
b11 $
b11 +
b11 0
b100000 )
12
b0 1
#33000
b10000000 "
b10000000 -
b10000000 %
b10000000 ,
b0 $
b0 +
b10000000 /
b0 0
b101 (
b100001 )
02
b1111111 1
#34000
b1 $
b1 +
b1 0
b100010 )
b10000000 1
#35000
1!
b0 "
b0 -
b10 $
b10 +
b10 0
b100011 )
#36000
0!
b10000000 "
b10000000 -
b11 $
b11 +
b11 0
b100100 )
12
b0 1
#37000
b11111110 "
b11111110 -
b11111110 %
b11111110 ,
b0 $
b0 +
b11111110 /
b0 0
b110 (
b100101 )
02
b10000000 1
#38000
b10 "
b10 -
b1 $
b1 +
b1 0
b100110 )
b11111110 1
#39000
1!
b0 "
b0 -
b10 $
b10 +
b10 0
b100111 )
b10 1
#40000
0!
b11111110 "
b11111110 -
b11 $
b11 +
b11 0
b101000 )
12
b0 1
#41000
b11111111 "
b11111111 -
b11111111 %
b11111111 ,
b0 $
b0 +
b11111111 /
b0 0
b111 (
b101001 )
02
b11111110 1
#42000
b1 "
b1 -
b1 $
b1 +
b1 0
b101010 )
b11111111 1
#43000
1!
b0 "
b0 -
b10 $
b10 +
b10 0
b101011 )
b1 1
#44000
0!
b11111111 "
b11111111 -
b11 $
b11 +
b11 0
b101100 )
12
b0 1
#45000
b1 "
b1 -
b0 %
b0 ,
b1 #
b1 *
b0 $
b0 +
b0 /
b1 .
b0 0
b1 '
b0 (
b101101 )
02
b11111111 1
#46000
b1 $
b1 +
b1 0
b101110 )
b1 1
#47000
1!
b0 "
b0 -
b10 $
b10 +
b10 0
b101111 )
#48000
0!
b1 "
b1 -
b11 $
b11 +
b11 0
b110000 )
12
b0 1
#49000
b10 "
b10 -
b1 %
b1 ,
b0 $
b0 +
b1 /
b0 0
b1 (
b110001 )
02
b1 1
#50000
1!
b0 "
b0 -
b1 $
b1 +
b1 0
b110010 )
b10 1
#51000
0!
b1 "
b1 -
b10 $
b10 +
b10 0
b110011 )
12
b0 1
#52000
b11 $
b11 +
b11 0
b110100 )
02
b1 1
#53000
b11 "
b11 -
b10 %
b10 ,
b0 $
b0 +
b10 /
b0 0
b10 (
b110101 )
#54000
b11111111 "
b11111111 -
b1 $
b1 +
b1 0
b110110 )
b11 1
#55000
1!
b0 "
b0 -
b10 $
b10 +
b10 0
b110111 )
b11111111 1
#56000
0!
b11 "
b11 -
b11 $
b11 +
b11 0
b111000 )
12
b0 1
#57000
b100 "
b100 -
b11 %
b11 ,
b0 $
b0 +
b11 /
b0 0
b11 (
b111001 )
02
b11 1
#58000
b11111110 "
b11111110 -
b1 $
b1 +
b1 0
b111010 )
b100 1
#59000
b1 "
b1 -
b10 $
b10 +
b10 0
b111011 )
b11111110 1
#60000
b11 "
b11 -
b11 $
b11 +
b11 0
b111100 )
b1 1
#61000
b10000000 "
b10000000 -
b1111111 %
b1111111 ,
b0 $
b0 +
b1111111 /
b0 0
b100 (
b111101 )
b11 1
#62000
b10000010 "
b10000010 -
b1 $
b1 +
b1 0
b111110 )
b10000000 1
#63000
b1 "
b1 -
b10 $
b10 +
b10 0
b111111 )
b10000010 1
#64000
b1111111 "
b1111111 -
b11 $
b11 +
b11 0
b1000000 )
b1 1
#65000
b10000001 "
b10000001 -
b10000000 %
b10000000 ,
b0 $
b0 +
b10000000 /
b0 0
b101 (
b1000001 )
b1111111 1
#66000
b1 $
b1 +
b1 0
b1000010 )
b10000001 1
#67000
1!
b0 "
b0 -
b10 $
b10 +
b10 0
b1000011 )
#68000
0!
b10000001 "
b10000001 -
b11 $
b11 +
b11 0
b1000100 )
12
b0 1
#69000
b11111111 "
b11111111 -
b11111110 %
b11111110 ,
b0 $
b0 +
b11111110 /
b0 0
b110 (
b1000101 )
02
b10000001 1
#70000
b11 "
b11 -
b1 $
b1 +
b1 0
b1000110 )
b11111111 1
#71000
1!
b0 "
b0 -
b10 $
b10 +
b10 0
b1000111 )
b11 1
#72000
0!
b11111111 "
b11111111 -
b11 $
b11 +
b11 0
b1001000 )
12
b0 1
#73000
1!
b0 "
b0 -
b11111111 %
b11111111 ,
b0 $
b0 +
b11111111 /
b0 0
b111 (
b1001001 )
02
b11111111 1
#74000
0!
b10 "
b10 -
b1 $
b1 +
b1 0
b1001010 )
12
b0 1
#75000
b1 "
b1 -
b10 $
b10 +
b10 0
b1001011 )
02
b10 1
#76000
b11111111 "
b11111111 -
b11 $
b11 +
b11 0
b1001100 )
b1 1
#77000
b10 "
b10 -
b0 %
b0 ,
b10 #
b10 *
b0 $
b0 +
b0 /
b10 .
b0 0
b10 '
b0 (
b1001101 )
b11111111 1
#78000
b1 $
b1 +
b1 0
b1001110 )
b10 1
#79000
1!
b0 "
b0 -
b10 $
b10 +
b10 0
b1001111 )
#80000
0!
b10 "
b10 -
b11 $
b11 +
b11 0
b1010000 )
12
b0 1
#81000
b11 "
b11 -
b1 %
b1 ,
b0 $
b0 +
b1 /
b0 0
b1 (
b1010001 )
02
b10 1
#82000
b1 "
b1 -
b1 $
b1 +
b1 0
b1010010 )
b11 1
#83000
1!
b0 "
b0 -
b10 $
b10 +
b10 0
b1010011 )
b1 1
#84000
0!
b11 "
b11 -
b11 $
b11 +
b11 0
b1010100 )
12
b0 1
#85000
b100 "
b100 -
b10 %
b10 ,
b0 $
b0 +
b10 /
b0 0
b10 (
b1010101 )
02
b11 1
#86000
1!
b0 "
b0 -
b1 $
b1 +
b1 0
b1010110 )
b100 1
#87000
0!
b10 "
b10 -
b10 $
b10 +
b10 0
b1010111 )
12
b0 1
#88000
b11 $
b11 +
b11 0
b1011000 )
02
b10 1
#89000
b101 "
b101 -
b11 %
b11 ,
b0 $
b0 +
b11 /
b0 0
b11 (
b1011001 )
#90000
b11111111 "
b11111111 -
b1 $
b1 +
b1 0
b1011010 )
b101 1
#91000
b10 "
b10 -
b10 $
b10 +
b10 0
b1011011 )
b11111111 1
#92000
b11 "
b11 -
b11 $
b11 +
b11 0
b1011100 )
b10 1
#93000
b10000001 "
b10000001 -
b1111111 %
b1111111 ,
b0 $
b0 +
b1111111 /
b0 0
b100 (
b1011101 )
b11 1
#94000
b10000011 "
b10000011 -
b1 $
b1 +
b1 0
b1011110 )
b10000001 1
#95000
b10 "
b10 -
b10 $
b10 +
b10 0
b1011111 )
b10000011 1
#96000
b1111111 "
b1111111 -
b11 $
b11 +
b11 0
b1100000 )
b10 1
#97000
b10000010 "
b10000010 -
b10000000 %
b10000000 ,
b0 $
b0 +
b10000000 /
b0 0
b101 (
b1100001 )
b1111111 1
#98000
b1 $
b1 +
b1 0
b1100010 )
b10000010 1
#99000
1!
b0 "
b0 -
b10 $
b10 +
b10 0
b1100011 )
#100000
0!
b10000010 "
b10000010 -
b11 $
b11 +
b11 0
b1100100 )
12
b0 1
#101000
1!
b0 "
b0 -
b11111110 %
b11111110 ,
b0 $
b0 +
b11111110 /
b0 0
b110 (
b1100101 )
02
b10000010 1
#102000
0!
b100 "
b100 -
b1 $
b1 +
b1 0
b1100110 )
12
b0 1
#103000
b10 "
b10 -
b10 $
b10 +
b10 0
b1100111 )
02
b100 1
#104000
b11111110 "
b11111110 -
b11 $
b11 +
b11 0
b1101000 )
b10 1
#105000
b1 "
b1 -
b11111111 %
b11111111 ,
b0 $
b0 +
b11111111 /
b0 0
b111 (
b1101001 )
b11111110 1
#106000
b11 "
b11 -
b1 $
b1 +
b1 0
b1101010 )
b1 1
#107000
b10 "
b10 -
b10 $
b10 +
b10 0
b1101011 )
b11 1
#108000
b11111111 "
b11111111 -
b11 $
b11 +
b11 0
b1101100 )
b10 1
#109000
b11 "
b11 -
b0 %
b0 ,
b11 #
b11 *
b0 $
b0 +
b0 /
b11 .
b0 0
b11 '
b0 (
b1101101 )
b11111111 1
#110000
b1 $
b1 +
b1 0
b1101110 )
b11 1
#111000
1!
b0 "
b0 -
b10 $
b10 +
b10 0
b1101111 )
#112000
0!
b11 "
b11 -
b11 $
b11 +
b11 0
b1110000 )
12
b0 1
#113000
b100 "
b100 -
b1 %
b1 ,
b0 $
b0 +
b1 /
b0 0
b1 (
b1110001 )
02
b11 1
#114000
b10 "
b10 -
b1 $
b1 +
b1 0
b1110010 )
b100 1
#115000
b1 "
b1 -
b10 $
b10 +
b10 0
b1110011 )
b10 1
#116000
b11 "
b11 -
b11 $
b11 +
b11 0
b1110100 )
b1 1
#117000
b101 "
b101 -
b10 %
b10 ,
b0 $
b0 +
b10 /
b0 0
b10 (
b1110101 )
b11 1
#118000
b1 "
b1 -
b1 $
b1 +
b1 0
b1110110 )
b101 1
#119000
b10 "
b10 -
b10 $
b10 +
b10 0
b1110111 )
b1 1
#120000
b11 "
b11 -
b11 $
b11 +
b11 0
b1111000 )
b10 1
#121000
b110 "
b110 -
b11 %
b11 ,
b0 $
b0 +
b11 /
b0 0
b11 (
b1111001 )
b11 1
#122000
1!
b0 "
b0 -
b1 $
b1 +
b1 0
b1111010 )
b110 1
#123000
0!
b11 "
b11 -
b10 $
b10 +
b10 0
b1111011 )
12
b0 1
#124000
b11 $
b11 +
b11 0
b1111100 )
02
b11 1
#125000
b10000010 "
b10000010 -
b1111111 %
b1111111 ,
b0 $
b0 +
b1111111 /
b0 0
b100 (
b1111101 )
#126000
b10000100 "
b10000100 -
b1 $
b1 +
b1 0
b1111110 )
b10000010 1
#127000
b11 "
b11 -
b10 $
b10 +
b10 0
b1111111 )
b10000100 1
#128000
b1111111 "
b1111111 -
b11 $
b11 +
b11 0
b10000000 )
b11 1
#129000
b10000011 "
b10000011 -
b10000000 %
b10000000 ,
b0 $
b0 +
b10000000 /
b0 0
b101 (
b10000001 )
b1111111 1
#130000
b1 $
b1 +
b1 0
b10000010 )
b10000011 1
#131000
1!
b0 "
b0 -
b10 $
b10 +
b10 0
b10000011 )
#132000
0!
b10000011 "
b10000011 -
b11 $
b11 +
b11 0
b10000100 )
12
b0 1
#133000
b1 "
b1 -
b11111110 %
b11111110 ,
b0 $
b0 +
b11111110 /
b0 0
b110 (
b10000101 )
02
b10000011 1
#134000
b101 "
b101 -
b1 $
b1 +
b1 0
b10000110 )
b1 1
#135000
b10 "
b10 -
b10 $
b10 +
b10 0
b10000111 )
b101 1
#136000
b11111111 "
b11111111 -
b11 $
b11 +
b11 0
b10001000 )
b10 1
#137000
b10 "
b10 -
b11111111 %
b11111111 ,
b0 $
b0 +
b11111111 /
b0 0
b111 (
b10001001 )
b11111111 1
#138000
b100 "
b100 -
b1 $
b1 +
b1 0
b10001010 )
b10 1
#139000
b11 "
b11 -
b10 $
b10 +
b10 0
b10001011 )
b100 1
#140000
b11111111 "
b11111111 -
b11 $
b11 +
b11 0
b10001100 )
b11 1
#141000
b1111111 "
b1111111 -
b0 %
b0 ,
b1111111 #
b1111111 *
b0 $
b0 +
b0 /
b1111111 .
b0 0
b100 '
b0 (
b10001101 )
b11111111 1
#142000
b1 $
b1 +
b1 0
b10001110 )
b1111111 1
#143000
1!
b0 "
b0 -
b10 $
b10 +
b10 0
b10001111 )
#144000
0!
b1111111 "
b1111111 -
b11 $
b11 +
b11 0
b10010000 )
12
b0 1
#145000
b10000000 "
b10000000 -
b1 %
b1 ,
b0 $
b0 +
b1 /
b0 0
b1 (
b10010001 )
02
b1111111 1
#146000
b1111110 "
b1111110 -
b1 $
b1 +
b1 0
b10010010 )
b10000000 1
#147000
b1 "
b1 -
b10 $
b10 +
b10 0
b10010011 )
b1111110 1
#148000
b1111111 "
b1111111 -
b11 $
b11 +
b11 0
b10010100 )
b1 1
#149000
b10000001 "
b10000001 -
b10 %
b10 ,
b0 $
b0 +
b10 /
b0 0
b10 (
b10010101 )
b1111111 1
#150000
b1111101 "
b1111101 -
b1 $
b1 +
b1 0
b10010110 )
b10000001 1
#151000
b10 "
b10 -
b10 $
b10 +
b10 0
b10010111 )
b1111101 1
#152000
b1111111 "
b1111111 -
b11 $
b11 +
b11 0
b10011000 )
b10 1
#153000
b10000010 "
b10000010 -
b11 %
b11 ,
b0 $
b0 +
b11 /
b0 0
b11 (
b10011001 )
b1111111 1
#154000
b1111100 "
b1111100 -
b1 $
b1 +
b1 0
b10011010 )
b10000010 1
#155000
b11 "
b11 -
b10 $
b10 +
b10 0
b10011011 )
b1111100 1
#156000
b1111111 "
b1111111 -
b11 $
b11 +
b11 0
b10011100 )
b11 1
#157000
b11111110 "
b11111110 -
b1111111 %
b1111111 ,
b0 $
b0 +
b1111111 /
b0 0
b100 (
b10011101 )
b1111111 1
#158000
1!
b0 "
b0 -
b1 $
b1 +
b1 0
b10011110 )
b11111110 1
#159000
0!
b1111111 "
b1111111 -
b10 $
b10 +
b10 0
b10011111 )
12
b0 1
#160000
b11 $
b11 +
b11 0
b10100000 )
02
b1111111 1
#161000
b11111111 "
b11111111 -
b10000000 %
b10000000 ,
b0 $
b0 +
b10000000 /
b0 0
b101 (
b10100001 )
#162000
b1 $
b1 +
b1 0
b10100010 )
b11111111 1
#163000
1!
b0 "
b0 -
b10 $
b10 +
b10 0
b10100011 )
#164000
0!
b11111111 "
b11111111 -
b11 $
b11 +
b11 0
b10100100 )
12
b0 1
#165000
b1111101 "
b1111101 -
b11111110 %
b11111110 ,
b0 $
b0 +
b11111110 /
b0 0
b110 (
b10100101 )
02
b11111111 1
#166000
b10000001 "
b10000001 -
b1 $
b1 +
b1 0
b10100110 )
b1111101 1
#167000
b1111110 "
b1111110 -
b10 $
b10 +
b10 0
b10100111 )
b10000001 1
#168000
b11111111 "
b11111111 -
b11 $
b11 +
b11 0
b10101000 )
b1111110 1
#169000
b1111110 "
b1111110 -
b11111111 %
b11111111 ,
b0 $
b0 +
b11111111 /
b0 0
b111 (
b10101001 )
b11111111 1
#170000
b10000000 "
b10000000 -
b1 $
b1 +
b1 0
b10101010 )
b1111110 1
#171000
b1111111 "
b1111111 -
b10 $
b10 +
b10 0
b10101011 )
b10000000 1
#172000
b11111111 "
b11111111 -
b11 $
b11 +
b11 0
b10101100 )
b1111111 1
#173000
b10000000 "
b10000000 -
b0 %
b0 ,
b10000000 #
b10000000 *
b0 $
b0 +
b0 /
b10000000 .
b0 0
b101 '
b0 (
b10101101 )
b11111111 1
#174000
b1 $
b1 +
b1 0
b10101110 )
b10000000 1
#175000
1!
b0 "
b0 -
b10 $
b10 +
b10 0
b10101111 )
#176000
0!
b10000000 "
b10000000 -
b11 $
b11 +
b11 0
b10110000 )
12
b0 1
#177000
b10000001 "
b10000001 -
b1 %
b1 ,
b0 $
b0 +
b1 /
b0 0
b1 (
b10110001 )
02
b10000000 1
#178000
b1111111 "
b1111111 -
b1 $
b1 +
b1 0
b10110010 )
b10000001 1
#179000
1!
b0 "
b0 -
b10 $
b10 +
b10 0
b10110011 )
b1111111 1
#180000
0!
b10000001 "
b10000001 -
b11 $
b11 +
b11 0
b10110100 )
12
b0 1
#181000
b10000010 "
b10000010 -
b10 %
b10 ,
b0 $
b0 +
b10 /
b0 0
b10 (
b10110101 )
02
b10000001 1
#182000
b1111110 "
b1111110 -
b1 $
b1 +
b1 0
b10110110 )
b10000010 1
#183000
1!
b0 "
b0 -
b10 $
b10 +
b10 0
b10110111 )
b1111110 1
#184000
0!
b10000010 "
b10000010 -
b11 $
b11 +
b11 0
b10111000 )
12
b0 1
#185000
b10000011 "
b10000011 -
b11 %
b11 ,
b0 $
b0 +
b11 /
b0 0
b11 (
b10111001 )
02
b10000010 1
#186000
b1111101 "
b1111101 -
b1 $
b1 +
b1 0
b10111010 )
b10000011 1
#187000
1!
b0 "
b0 -
b10 $
b10 +
b10 0
b10111011 )
b1111101 1
#188000
0!
b10000011 "
b10000011 -
b11 $
b11 +
b11 0
b10111100 )
12
b0 1
#189000
b11111111 "
b11111111 -
b1111111 %
b1111111 ,
b0 $
b0 +
b1111111 /
b0 0
b100 (
b10111101 )
02
b10000011 1
#190000
b1 "
b1 -
b1 $
b1 +
b1 0
b10111110 )
b11111111 1
#191000
1!
b0 "
b0 -
b10 $
b10 +
b10 0
b10111111 )
b1 1
#192000
0!
b11111111 "
b11111111 -
b11 $
b11 +
b11 0
b11000000 )
12
b0 1
#193000
1!
b0 "
b0 -
b10000000 %
b10000000 ,
b0 $
b0 +
b10000000 /
b0 0
b101 (
b11000001 )
02
b11111111 1
#194000
b1 $
b1 +
b1 0
b11000010 )
12
b0 1
#195000
0!
b10000000 "
b10000000 -
b10 $
b10 +
b10 0
b11000011 )
#196000
b11 $
b11 +
b11 0
b11000100 )
02
b10000000 1
#197000
b1111110 "
b1111110 -
b11111110 %
b11111110 ,
b0 $
b0 +
b11111110 /
b0 0
b110 (
b11000101 )
#198000
b10000010 "
b10000010 -
b1 $
b1 +
b1 0
b11000110 )
b1111110 1
#199000
b10000000 "
b10000000 -
b10 $
b10 +
b10 0
b11000111 )
b10000010 1
#200000
b11111110 "
b11111110 -
b11 $
b11 +
b11 0
b11001000 )
b10000000 1
#201000
b1111111 "
b1111111 -
b11111111 %
b11111111 ,
b0 $
b0 +
b11111111 /
b0 0
b111 (
b11001001 )
b11111110 1
#202000
b10000001 "
b10000001 -
b1 $
b1 +
b1 0
b11001010 )
b1111111 1
#203000
b10000000 "
b10000000 -
b10 $
b10 +
b10 0
b11001011 )
b10000001 1
#204000
b11111111 "
b11111111 -
b11 $
b11 +
b11 0
b11001100 )
b10000000 1
#205000
b11111110 "
b11111110 -
b0 %
b0 ,
b11111110 #
b11111110 *
b0 $
b0 +
b0 /
b11111110 .
b0 0
b110 '
b0 (
b11001101 )
b11111111 1
#206000
b1 $
b1 +
b1 0
b11001110 )
b11111110 1
#207000
1!
b0 "
b0 -
b10 $
b10 +
b10 0
b11001111 )
#208000
0!
b11111110 "
b11111110 -
b11 $
b11 +
b11 0
b11010000 )
12
b0 1
#209000
b11111111 "
b11111111 -
b1 %
b1 ,
b0 $
b0 +
b1 /
b0 0
b1 (
b11010001 )
02
b11111110 1
#210000
b11111101 "
b11111101 -
b1 $
b1 +
b1 0
b11010010 )
b11111111 1
#211000
1!
b0 "
b0 -
b10 $
b10 +
b10 0
b11010011 )
b11111101 1
#212000
0!
b11111111 "
b11111111 -
b11 $
b11 +
b11 0
b11010100 )
12
b0 1
#213000
1!
b0 "
b0 -
b10 %
b10 ,
b0 $
b0 +
b10 /
b0 0
b10 (
b11010101 )
02
b11111111 1
#214000
0!
b11111100 "
b11111100 -
b1 $
b1 +
b1 0
b11010110 )
12
b0 1
#215000
b10 "
b10 -
b10 $
b10 +
b10 0
b11010111 )
02
b11111100 1
#216000
b11111110 "
b11111110 -
b11 $
b11 +
b11 0
b11011000 )
b10 1
#217000
b1 "
b1 -
b11 %
b11 ,
b0 $
b0 +
b11 /
b0 0
b11 (
b11011001 )
b11111110 1
#218000
b11111011 "
b11111011 -
b1 $
b1 +
b1 0
b11011010 )
b1 1
#219000
b10 "
b10 -
b10 $
b10 +
b10 0
b11011011 )
b11111011 1
#220000
b11111111 "
b11111111 -
b11 $
b11 +
b11 0
b11011100 )
b10 1
#221000
b1111101 "
b1111101 -
b1111111 %
b1111111 ,
b0 $
b0 +
b1111111 /
b0 0
b100 (
b11011101 )
b11111111 1
#222000
b1111111 "
b1111111 -
b1 $
b1 +
b1 0
b11011110 )
b1111101 1
#223000
b1111110 "
b1111110 -
b10 $
b10 +
b10 0
b11011111 )
b1111111 1
#224000
b11111111 "
b11111111 -
b11 $
b11 +
b11 0
b11100000 )
b1111110 1
#225000
b1111110 "
b1111110 -
b10000000 %
b10000000 ,
b0 $
b0 +
b10000000 /
b0 0
b101 (
b11100001 )
b11111111 1
#226000
b1 $
b1 +
b1 0
b11100010 )
b1111110 1
#227000
b10000000 "
b10000000 -
b10 $
b10 +
b10 0
b11100011 )
#228000
b11111110 "
b11111110 -
b11 $
b11 +
b11 0
b11100100 )
b10000000 1
#229000
b11111100 "
b11111100 -
b11111110 %
b11111110 ,
b0 $
b0 +
b11111110 /
b0 0
b110 (
b11100101 )
b11111110 1
#230000
1!
b0 "
b0 -
b1 $
b1 +
b1 0
b11100110 )
b11111100 1
#231000
0!
b11111110 "
b11111110 -
b10 $
b10 +
b10 0
b11100111 )
12
b0 1
#232000
b11 $
b11 +
b11 0
b11101000 )
02
b11111110 1
#233000
b11111101 "
b11111101 -
b11111111 %
b11111111 ,
b0 $
b0 +
b11111111 /
b0 0
b111 (
b11101001 )
#234000
b11111111 "
b11111111 -
b1 $
b1 +
b1 0
b11101010 )
b11111101 1
#235000
b11111110 "
b11111110 -
b10 $
b10 +
b10 0
b11101011 )
b11111111 1
#236000
b11111111 "
b11111111 -
b11 $
b11 +
b11 0
b11101100 )
b11111110 1
#237000
b0 %
b0 ,
b11111111 #
b11111111 *
b0 $
b0 +
b0 /
b11111111 .
b0 0
b111 '
b0 (
b11101101 )
b11111111 1
#238000
b1 $
b1 +
b1 0
b11101110 )
#239000
1!
b0 "
b0 -
b10 $
b10 +
b10 0
b11101111 )
#240000
0!
b11111111 "
b11111111 -
b11 $
b11 +
b11 0
b11110000 )
12
b0 1
#241000
1!
b0 "
b0 -
b1 %
b1 ,
b0 $
b0 +
b1 /
b0 0
b1 (
b11110001 )
02
b11111111 1
#242000
0!
b11111110 "
b11111110 -
b1 $
b1 +
b1 0
b11110010 )
12
b0 1
#243000
b1 "
b1 -
b10 $
b10 +
b10 0
b11110011 )
02
b11111110 1
#244000
b11111111 "
b11111111 -
b11 $
b11 +
b11 0
b11110100 )
b1 1
#245000
b1 "
b1 -
b10 %
b10 ,
b0 $
b0 +
b10 /
b0 0
b10 (
b11110101 )
b11111111 1
#246000
b11111101 "
b11111101 -
b1 $
b1 +
b1 0
b11110110 )
b1 1
