imem.v
module imem (
    input  wire [7:0] addr,
    output wire [7:0] instr
);

    reg [7:0] mem [0:255];

    initial begin
        $readmemh("program.hex", mem);
    end

    assign instr = mem[addr];

endmodule

tb_imem.v
`timescale 1ns/1ps

module tb_imem;
    reg  [7:0] addr;
    wire [7:0] instr;

    imem dut (
        .addr(addr),
        .instr(instr)
    );

    /*
     * Dummy program.hex format for $readmemh:
     *
     *   - One 8-bit value per line, written in hexadecimal (no "0x" prefix).
     *   - Optional line comments with // (supported by Icarus Verilog in hex files).
     *   - First line loads into mem[0], second into mem[1], and so on.
     *
     * Example file (program.hex):
     *
     *   DE
     *   AD
     *   BE
     *   EF
     *   00
     *   11
     *
     * Run vvp from the directory that contains program.hex (usually the project root).
     */

    integer a;

    initial begin
        $dumpfile("imem_waves.vcd");
        $dumpvars(0, tb_imem);

        addr = 8'h00;
        #1;
        for (a = 0; a <= 5; a = a + 1) begin
            addr = a[7:0];
            #10;
            $display("addr=%0d (0x%02h)  instr=0x%02h", addr, addr, instr);
        end

        // Edge: last byte in the ROM image
        addr = 8'hFF;
        #10;
        $display("EDGE [High-address access]: addr=0x%02h (last location)  instr=0x%02h",
            addr, instr);

        // Edge: jump from a low address to mid-range in one step (async read)
        addr = 8'h02;
        #1;
        addr = 8'h80;
        #10;
        $display("EDGE [Random access jump]: after low addr, addr=0x%02h  instr=0x%02h",
            addr, instr);

        // Edge: return to first location
        addr = 8'h00;
        #10;
        $display("EDGE [Wrap-around / reset to start]: addr=0x%02h  instr=0x%02h (first instr)",
            addr, instr);

        $finish;
    end
endmodule

.gitignore/imem_waves.vcd
$date
	Sun Mar 22 14:03:19 2026
$end
$version
	Icarus Verilog
$end
$timescale
	1ps
$end
$scope module tb_imem $end
$var wire 8 ! instr [7:0] $end
$var reg 8 " addr [7:0] $end
$var integer 32 # a [31:0] $end
$scope module dut $end
$var wire 8 $ addr [7:0] $end
$var wire 8 % instr [7:0] $end
$upscope $end
$upscope $end
$enddefinitions $end
$comment Show the parameter values. $end
$dumpall
$end
#0
$dumpvars
b11011110 %
b0 $
bx #
b0 "
b11011110 !
$end
#1000
b0 #
#11000
b10101101 !
b10101101 %
b1 "
b1 $
b1 #
#21000
b10111110 !
b10111110 %
b10 "
b10 $
b10 #
#31000
b11101111 !
b11101111 %
b11 "
b11 $
b11 #
#41000
b0 !
b0 %
b100 "
b100 $
b100 #
#51000
b10001 !
b10001 %
b101 "
b101 $
b101 #
#61000
b0 !
b0 %
b11111111 "
b11111111 $
b110 #
#71000
b0 !
b0 %
b10000000 "
b10000000 $
#81000
b11011110 !
b11011110 %
b0 "
b0 $
