src/pc.v
module pc (
    input  wire       clk,
    input  wire       reset,
    input  wire       is_branch,
    input  wire       is_bne,
    input  wire       zero,
    input  wire [5:0] branch_offset,
    output reg  [7:0] pc_out
);

    wire branch_taken;
    assign branch_taken = (is_branch && zero) || (is_bne && !zero);

    // Asynchronous reset: clear immediately when reset is asserted.
    // Otherwise increment on each rising clock edge.
    // BEQ branches when equal; BNE branches when not equal. Same signed offset.
    always @(posedge clk or posedge reset) begin
        if (reset)
            pc_out <= 8'd0;
        else if (branch_taken)
            pc_out <= pc_out + 8'd1 + {{2{branch_offset[5]}}, branch_offset};
        else
            pc_out <= pc_out + 8'd1;
    end

endmodule

tb_pc.v
`timescale 1ns/1ps

module tb_pc;
    reg        clk;
    reg        reset;
    wire [7:0] pc_out;

    pc dut (
        .clk(clk),
        .reset(reset),
        .pc_out(pc_out)
    );

    // Clock: 10 ns period
    initial begin
        clk = 1'b0;
        forever #5 clk = ~clk;
    end

    // Print PC after each clock edge (small delay so nonblocking updates are visible).
    always @(posedge clk) begin
        #0.1;
        $display("time=%0t  clk=1  reset=%b  pc_out=%0d (0x%02h)", $time, reset, pc_out, pc_out);
    end

    initial begin
        $dumpfile("pc_waves.vcd");
        $dumpvars(0, tb_pc);

        reset = 1'b1;
        #12;
        reset = 1'b0;

        // Run: 15 rising edges after release of initial reset (pc should reach 15).
        repeat (15) @(posedge clk);
        // Assert reset between clock edges so the 15th increment is visible before clear.
        #2;
        reset = 1'b1;
        #7;
        reset = 1'b0;

        // A few more cycles after mid reset
        repeat (5) @(posedge clk);

        $display("Simulation complete.");
        $finish;
    end
endmodule

.gitignore/pc_waves.vcd
$date
	Sun Mar 22 12:51:56 2026
$end
$version
	Icarus Verilog
$end
$timescale
	1ps
$end
$scope module tb_pc $end
$var wire 8 ! pc_out [7:0] $end
$var reg 1 " clk $end
$var reg 1 # reset $end
$scope module dut $end
$var wire 1 " clk $end
$var wire 1 # reset $end
$var reg 8 $ pc_out [7:0] $end
$upscope $end
$upscope $end
$enddefinitions $end
$comment Show the parameter values. $end
$dumpall
$end
#0
$dumpvars
b0 $
1#
0"
b0 !
$end
#5000
1"
#10000
0"
#12000
0#
#15000
b1 !
b1 $
1"
#20000
0"
#25000
b10 !
b10 $
1"
#30000
0"
#35000
b11 !
b11 $
1"
#40000
0"
#45000
b100 !
b100 $
1"
#50000
0"
#55000
b101 !
b101 $
1"
#60000
0"
#65000
b110 !
b110 $
1"
#70000
0"
#75000
b111 !
b111 $
1"
#80000
0"
#85000
b1000 !
b1000 $
1"
#90000
0"
#95000
b1001 !
b1001 $
1"
#100000
0"
#105000
b1010 !
b1010 $
1"
#110000
0"
#115000
b1011 !
b1011 $
1"
#120000
0"
#125000
b1100 !
b1100 $
1"
#130000
0"
#135000
b1101 !
b1101 $
1"
#140000
0"
#145000
b1110 !
b1110 $
1"
#150000
0"
#155000
b1111 !
b1111 $
1"
#157000
b0 !
b0 $
1#
#160000
0"
#164000
0#
#165000
b1 !
b1 $
1"
#170000
0"
#175000
b10 !
b10 $
1"
#180000
0"
#185000
b11 !
b11 $
1"
#190000
0"
#195000
b100 !
b100 $
1"
#200000
0"
#205000
b101 !
b101 $
1"
