src/regfile.v
module regfile (
    input  wire        clk,
    input  wire        we,
    input  wire [2:0]  read_addr1,
    input  wire [2:0]  read_addr2,
    input  wire [2:0]  write_addr,
    input  wire [7:0]  write_data,
    output wire [7:0]  read_data1,
    output wire [7:0]  read_data2
);

    // 8 registers, 8-bit each
    reg [7:0] regs [0:7];

    // Asynchronous read (combinational)
    assign read_data1 = (read_addr1 == 3'b000) ? 8'h00 : regs[read_addr1];
    assign read_data2 = (read_addr2 == 3'b000) ? 8'h00 : regs[read_addr2];

    // Synchronous write (posedge clk), ignore writes to R0
    always @(posedge clk) begin
        if (we && (write_addr != 3'b000)) begin
            regs[write_addr] <= write_data;
        end
    end

    // Optional initialization for clean simulation starts
    integer i;
    initial begin
        regs[0] = 8'h00;
        for (i = 1; i < 8; i = i + 1) begin
            regs[i] = 8'h00;
        end
    end

endmodule

tests/tb_regfile.v
`timescale 1ns/1ps

module tb_regfile;
    reg         clk;
    reg         we;
    reg  [2:0]  read_addr1;
    reg  [2:0]  read_addr2;
    reg  [2:0]  write_addr;
    reg  [7:0]  write_data;
    wire [7:0]  read_data1;
    wire [7:0]  read_data2;

    regfile dut (
        .clk(clk),
        .we(we),
        .read_addr1(read_addr1),
        .read_addr2(read_addr2),
        .write_addr(write_addr),
        .write_data(write_data),
        .read_data1(read_data1),
        .read_data2(read_data2)
    );

    integer errors;
    integer tests;

    task check_eq;
        input [7:0] got;
        input [7:0] exp;
        input [31:0] test_id;
        begin
            tests = tests + 1;
            if (got !== exp) begin
                errors = errors + 1;
                $display("FAIL: test_id=%0d got=%h exp=%h (t=%0t)", test_id, got, exp, $time);
            end
        end
    endtask

    task check_zero;
        input [7:0] got;
        input [31:0] test_id;
        begin
            check_eq(got, 8'h00, test_id);
        end
    endtask

    // Clock: 10ns period
    initial begin
        clk = 1'b0;
        forever #5 clk = ~clk;
    end

    initial begin
        $dumpfile("regfile_waves.vcd");
        $dumpvars(0, tb_regfile);

        errors = 0;
        tests  = 0;

        // Defaults
        we = 1'b0;
        read_addr1 = 3'b000;
        read_addr2 = 3'b000;
        write_addr = 3'b000;
        write_data = 8'h00;

        // Allow initial block init + a small time step
        #2;

        // R0 should read as 0 initially.
        check_zero(read_data1, 1);
        check_zero(read_data2, 2);

        // Write R1, R2, R7
        @(negedge clk);
        we = 1'b1;
        write_addr = 3'd1;
        write_data = 8'hAA;

        @(negedge clk);
        write_addr = 3'd2;
        write_data = 8'h55;

        @(negedge clk);
        write_addr = 3'd7;
        write_data = 8'h3C;

        @(negedge clk);
        we = 1'b0;
        write_addr = 3'd0;
        write_data = 8'h00;

        // Give time for last posedge write to take effect
        #2;

        // Verify synchronous writes took effect
        read_addr1 = 3'd1;
        read_addr2 = 3'd2;
        #1; // async read settle
        check_eq(read_data1, 8'hAA, 3);
        check_eq(read_data2, 8'h55, 4);

        read_addr1 = 3'd7;
        read_addr2 = 3'd0;
        #1; // async read settle
        check_eq(read_data1, 8'h3C, 5);
        check_zero(read_data2, 6);

        // Attempt to write non-zero to R0; should be ignored.
        @(negedge clk);
        we = 1'b1;
        write_addr = 3'd0;
        write_data = 8'hFF;

        @(negedge clk);
        we = 1'b0;
        write_addr = 3'd0;
        write_data = 8'h00;

        // Let the posedge pass
        #2;

        // R0 must remain 0
        read_addr1 = 3'd0;
        read_addr2 = 3'd1;
        #1;
        check_zero(read_data1, 7);
        check_eq(read_data2, 8'hAA, 8);

        // Explicit async read behavior check (no clock edge)
        // Change addresses and ensure outputs update immediately.
        read_addr1 = 3'd1;
        read_addr2 = 3'd2;
        #1;
        check_eq(read_data1, 8'hAA, 9);
        check_eq(read_data2, 8'h55, 10);

        read_addr1 = 3'd2;
        read_addr2 = 3'd7;
        #1;
        check_eq(read_data1, 8'h55, 11);
        check_eq(read_data2, 8'h3C, 12);

        if (errors == 0) begin
            $display("PASS: %0d tests passed.", tests);
        end else begin
            $display("DONE: %0d tests, %0d errors.", tests, errors);
        end

        $finish;
    end

endmodule

.gitignore/regfile_waves.vcd
$date
	Sat Mar 21 18:30:45 2026
$end
$version
	Icarus Verilog
$end
$timescale
	1ps
$end
$scope module tb_regfile $end
$var wire 8 ! read_data2 [7:0] $end
$var wire 8 " read_data1 [7:0] $end
$var reg 1 # clk $end
$var reg 3 $ read_addr1 [2:0] $end
$var reg 3 % read_addr2 [2:0] $end
$var reg 1 & we $end
$var reg 3 ' write_addr [2:0] $end
$var reg 8 ( write_data [7:0] $end
$var integer 32 ) errors [31:0] $end
$var integer 32 * tests [31:0] $end
$scope module dut $end
$var wire 1 # clk $end
$var wire 3 + read_addr1 [2:0] $end
$var wire 3 , read_addr2 [2:0] $end
$var wire 1 & we $end
$var wire 3 - write_addr [2:0] $end
$var wire 8 . write_data [7:0] $end
$var wire 8 / read_data2 [7:0] $end
$var wire 8 0 read_data1 [7:0] $end
$var integer 32 1 i [31:0] $end
$upscope $end
$scope task check_eq $end
$var reg 8 2 exp [7:0] $end
$var reg 8 3 got [7:0] $end
$var reg 32 4 test_id [31:0] $end
$upscope $end
$scope task check_zero $end
$var reg 8 5 got [7:0] $end
$var reg 32 6 test_id [31:0] $end
$upscope $end
$upscope $end
$enddefinitions $end
$comment Show the parameter values. $end
$dumpall
$end
#0
$dumpvars
bx 6
bx 5
bx 4
bx 3
bx 2
b1000 1
b0 0
b0 /
b0 .
b0 -
b0 ,
b0 +
b0 *
b0 )
b0 (
b0 '
0&
b0 %
b0 $
0#
b0 "
b0 !
$end
#2000
b10 *
b10 4
b0 2
b0 3
b10 6
b0 5
#5000
1#
#10000
b10101010 (
b10101010 .
b1 '
b1 -
1&
0#
#15000
1#
#20000
b1010101 (
b1010101 .
b10 '
b10 -
0#
#25000
1#
#30000
b111100 (
b111100 .
b111 '
b111 -
0#
#35000
1#
#40000
b0 (
b0 .
b0 '
b0 -
0&
0#
#42000
b1010101 !
b1010101 /
b10101010 "
b10101010 0
b10 %
b10 ,
b1 $
b1 +
#43000
b0 !
b0 /
b111100 "
b111100 0
b0 %
b0 ,
b111 $
b111 +
b100 *
b100 4
b1010101 2
b1010101 3
#44000
b110 6
b110 *
b110 4
b0 2
b0 3
#45000
1#
#50000
b11111111 (
b11111111 .
1&
0#
#55000
1#
#60000
b0 (
b0 .
0&
0#
#62000
b10101010 !
b10101010 /
b0 "
b0 0
b1 %
b1 ,
b0 $
b0 +
#63000
b1010101 !
b1010101 /
b10101010 "
b10101010 0
b10 %
b10 ,
b1 $
b1 +
b10101010 2
b10101010 3
b1000 *
b1000 4
b111 6
#64000
b111100 !
b111100 /
b1010101 "
b1010101 0
b111 %
b111 ,
b10 $
b10 +
b1010101 2
b1010101 3
b1010 *
b1010 4
#65000
b111100 2
b111100 3
b1100 *
b1100 4
1#
